parabellum/__init__.py
parabellum/aid.py
parabellum/env.py
parabellum/geo.py
parabellum/gun.py
parabellum/model.py
parabellum/pcg.py
parabellum/ppo.py
parabellum/run.py
parabellum/terrain_db.py
parabellum/types.py
parabellum/vis.py
parabellum-0.5.13.dist-info/METADATA
parabellum-0.5.13.dist-info/WHEEL
parabellum-0.5.13.dist-info/RECORD
